actseg/__about__.py
actseg/__init__.py
actseg/eval/__init__.py
actseg/eval/base.py
actseg/eval/frame.py
actseg/eval/segment.py
actseg/eval/external/__init__.py
actseg/eval/external/isba_code.py
actseg/eval/external/mstcn_code.py
actseg/utils/__init__.py
actseg-0.1.0.dist-info/LICENSE
actseg-0.1.0.dist-info/METADATA
actseg-0.1.0.dist-info/WHEEL
actseg-0.1.0.dist-info/top_level.txt
actseg-0.1.0.dist-info/RECORD
