Metadata-Version: 2.1
Name: actseg
Version: 0.1.0
Summary: A utility for action segmentation research: evaluation and others
Home-page: https://github.com/actseg/actseg/
Author: Yasser Souri
Author-email: yassersouri@gmail.com
License: UNKNOWN
Project-URL: Bug Reports, https://github.com/actseg/actseg/issues
Project-URL: Source, https://github.com/actseg/actseg/
Keywords: action segmentation,video understanding
Platform: UNKNOWN
Classifier: Development Status :: 3 - Alpha
Classifier: Intended Audience :: Developers
Classifier: Topic :: Scientific/Engineering :: Artificial Intelligence
Classifier: License :: OSI Approved :: MIT License
Classifier: Programming Language :: Python :: 3
Classifier: Programming Language :: Python :: 3.7
Classifier: Programming Language :: Python :: 3.8
Classifier: Programming Language :: Python :: 3.9
Classifier: Programming Language :: Python :: 3.10
Requires-Python: >=3.7, <4
License-File: LICENSE
Requires-Dist: numpy
Provides-Extra: dev
Requires-Dist: pytest ; extra == 'dev'
Requires-Dist: check-manifest ; extra == 'dev'
